{"match":{"startDateTime":1685060290,"chatEvents":[{"type":5,"fromHeroId":97,"toHeroId":{},"value":330},{"type":12,"fromHeroId":{},"toHeroId":{},"value":0},{"type":10,"fromHeroId":{},"toHeroId":{},"value":0},{"type":11,"fromHeroId":{},"toHeroId":{},"value":0},{"type":11,"fromHeroId":{},"toHeroId":{},"value":0},{"type":12,"fromHeroId":{},"toHeroId":{},"value":0},{"type":3,"fromHeroId":98,"toHeroId":{},"value":3},{"type":12,"fromHeroId":{},"toHeroId":{},"value":0},{"type":12,"fromHeroId":{},"toHeroId":{},"value":0},{"type":1000,"fromHeroId":98,"toHeroId":97,"value":50},{"type":12,"fromHeroId":{},"toHeroId":{},"value":0},{"type":3,"fromHeroId":97,"toHeroId":{},"value":3},{"type":3,"fromHeroId":97,"toHeroId":{},"value":3},{"type":3,"fromHeroId":98,"toHeroId":{},"value":3},{"type":12,"fromHeroId":{},"toHeroId":{},"value":0},{"type":3,"fromHeroId":97,"toHeroId":{},"value":3},{"type":12,"fromHeroId":{},"toHeroId":{},"value":0},{"type":3,"fromHeroId":97,"toHeroId":{},"value":3},{"type":12,"fromHeroId":{},"toHeroId":{},"value":0},{"type":1000,"fromHeroId":98,"toHeroId":97,"value":50},{"type":3,"fromHeroId":97,"toHeroId":{},"value":3},{"type":91,"fromHeroId":18,"toHeroId":{},"value":0},{"type":3,"fromHeroId":97,"toHeroId":{},"value":3},{"type":3,"fromHeroId":97,"toHeroId":{},"value":3},{"type":3,"fromHeroId":97,"toHeroId":{},"value":3},{"type":91,"fromHeroId":69,"toHeroId":{},"value":0},{"type":15,"fromHeroId":126,"toHeroId":{},"value":0},{"type":15,"fromHeroId":86,"toHeroId":{},"value":0},{"type":15,"fromHeroId":120,"toHeroId":{},"value":0},{"type":15,"fromHeroId":101,"toHeroId":{},"value":0},{"type":15,"fromHeroId":18,"toHeroId":{},"value":0},{"type":15,"fromHeroId":69,"toHeroId":{},"value":0},{"type":15,"fromHeroId":97,"toHeroId":{},"value":0},{"type":15,"fromHeroId":98,"toHeroId":{},"value":0},{"type":15,"fromHeroId":87,"toHeroId":{},"value":0},{"type":15,"fromHeroId":112,"toHeroId":{},"value":0}],"players":[{"steamAccountId":186837494,"heroId":112,"dotaPlus":{}},{"steamAccountId":383867949,"heroId":126,"dotaPlus":{"level":14}},{"steamAccountId":85696663,"heroId":86,"dotaPlus":{"level":27}},{"steamAccountId":308163407,"heroId":69,"dotaPlus":{"level":14}},{"steamAccountId":155162307,"heroId":18,"dotaPlus":{"level":26}},{"steamAccountId":1171243748,"heroId":97,"dotaPlus":{}},{"steamAccountId":408729743,"heroId":98,"dotaPlus":{"level":28}},{"steamAccountId":352545711,"heroId":120,"dotaPlus":{"level":16}},{"steamAccountId":119631156,"heroId":87,"dotaPlus":{}},{"steamAccountId":157989498,"heroId":101,"dotaPlus":{}}]}}
