{"match":{"startDateTime":1686088534,"players":[{"steamAccountId":86822085,"dotaPlus":{"level":21}},{"steamAccountId":131303632,"dotaPlus":{"level":15}},{"steamAccountId":84853828,"dotaPlus":{"level":11}},{"steamAccountId":81306398,"dotaPlus":{"level":20}},{"steamAccountId":107579895,"dotaPlus":{"level":20}},{"steamAccountId":1171243748,"dotaPlus":{"level":23}},{"steamAccountId":914221413,"dotaPlus":{"level":12}},{"steamAccountId":101779337,"dotaPlus":{}},{"steamAccountId":352623024,"dotaPlus":{"level":11}},{"steamAccountId":99796146,"dotaPlus":{}}]}}
