{"match":{"startDateTime":1686925167,"chatEvents":[{"type":5,"fromHeroId":66,"toHeroId":{},"value":329},{"type":11,"fromHeroId":{},"toHeroId":{},"value":0},{"type":11,"fromHeroId":{},"toHeroId":{},"value":0},{"type":12,"fromHeroId":{},"toHeroId":{},"value":0},{"type":12,"fromHeroId":{},"toHeroId":{},"value":0},{"type":3,"fromHeroId":98,"toHeroId":{},"value":3},{"type":1000,"fromHeroId":10,"toHeroId":39,"value":50},{"type":3,"fromHeroId":53,"toHeroId":{},"value":2},{"type":12,"fromHeroId":{},"toHeroId":{},"value":0},{"type":12,"fromHeroId":{},"toHeroId":{},"value":0},{"type":3,"fromHeroId":112,"toHeroId":{},"value":3},{"type":10,"fromHeroId":{},"toHeroId":{},"value":0},{"type":12,"fromHeroId":{},"toHeroId":{},"value":0},{"type":11,"fromHeroId":{},"toHeroId":{},"value":0},{"type":34,"fromHeroId":10,"toHeroId":{},"value":0},{"type":15,"fromHeroId":10,"toHeroId":{},"value":0},{"type":19,"fromHeroId":10,"toHeroId":{},"value":0},{"type":36,"fromHeroId":39,"toHeroId":{},"value":0},{"type":3,"fromHeroId":53,"toHeroId":{},"value":2},{"type":3,"fromHeroId":66,"toHeroId":{},"value":2},{"type":4,"fromHeroId":10,"toHeroId":{},"value":55},{"type":3,"fromHeroId":53,"toHeroId":{},"value":2},{"type":3,"fromHeroId":53,"toHeroId":{},"value":2},{"type":12,"fromHeroId":{},"toHeroId":{},"value":0},{"type":3,"fromHeroId":138,"toHeroId":{},"value":2},{"type":3,"fromHeroId":138,"toHeroId":{},"value":2},{"type":12,"fromHeroId":{},"toHeroId":{},"value":0},{"type":91,"fromHeroId":105,"toHeroId":{},"value":0},{"type":3,"fromHeroId":138,"toHeroId":{},"value":2},{"type":12,"fromHeroId":{},"toHeroId":{},"value":0},{"type":28,"fromHeroId":{},"toHeroId":{},"value":0},{"type":3,"fromHeroId":138,"toHeroId":{},"value":2},{"type":3,"fromHeroId":53,"toHeroId":{},"value":2},{"type":15,"fromHeroId":39,"toHeroId":{},"value":0},{"type":15,"fromHeroId":71,"toHeroId":{},"value":0},{"type":15,"fromHeroId":66,"toHeroId":{},"value":0},{"type":15,"fromHeroId":105,"toHeroId":{},"value":0},{"type":15,"fromHeroId":98,"toHeroId":{},"value":0},{"type":15,"fromHeroId":138,"toHeroId":{},"value":0},{"type":15,"fromHeroId":53,"toHeroId":{},"value":0},{"type":15,"fromHeroId":112,"toHeroId":{},"value":0},{"type":15,"fromHeroId":103,"toHeroId":{},"value":0},{"type":15,"fromHeroId":10,"toHeroId":{},"value":0},{"type":11,"fromHeroId":{},"toHeroId":{},"value":0}],"players":[{"steamAccountId":88271237,"heroId":53,"dotaPlus":{"level":30}},{"steamAccountId":94054712,"heroId":39,"dotaPlus":{"level":16}},{"steamAccountId":106573901,"heroId":138,"dotaPlus":{}},{"steamAccountId":187824320,"heroId":71,"dotaPlus":{}},{"steamAccountId":159020918,"heroId":66,"dotaPlus":{"level":30}},{"steamAccountId":41231571,"heroId":98,"dotaPlus":{"level":16}},{"steamAccountId":122049498,"heroId":10,"dotaPlus":{"level":30}},{"steamAccountId":18180970,"heroId":103,"dotaPlus":{}},{"steamAccountId":193884241,"heroId":105,"dotaPlus":{"level":13}},{"steamAccountId":113435203,"heroId":112,"dotaPlus":{}}]}}
