{"match":{"startDateTime":1688625050,"chatEvents":[{"type":34,"fromHeroId":58,"toHeroId":{},"value":0},{"type":36,"fromHeroId":128,"toHeroId":{},"value":0},{"type":1000,"fromHeroId":18,"toHeroId":86,"value":50},{"type":5,"fromHeroId":87,"toHeroId":{},"value":333},{"type":11,"fromHeroId":{},"toHeroId":{},"value":0},{"type":12,"fromHeroId":{},"toHeroId":{},"value":0},{"type":12,"fromHeroId":{},"toHeroId":{},"value":0},{"type":114,"fromHeroId":87,"toHeroId":{},"value":3},{"type":12,"fromHeroId":{},"toHeroId":{},"value":0},{"type":3,"fromHeroId":61,"toHeroId":{},"value":3},{"type":12,"fromHeroId":{},"toHeroId":{},"value":0},{"type":3,"fromHeroId":86,"toHeroId":{},"value":3},{"type":114,"fromHeroId":58,"toHeroId":{},"value":5},{"type":114,"fromHeroId":58,"toHeroId":{},"value":5},{"type":3,"fromHeroId":15,"toHeroId":{},"value":3},{"type":3,"fromHeroId":129,"toHeroId":{},"value":2},{"type":114,"fromHeroId":58,"toHeroId":{},"value":5},{"type":12,"fromHeroId":{},"toHeroId":{},"value":0},{"type":3,"fromHeroId":128,"toHeroId":{},"value":3},{"type":12,"fromHeroId":{},"toHeroId":{},"value":0},{"type":3,"fromHeroId":52,"toHeroId":{},"value":2},{"type":12,"fromHeroId":{},"toHeroId":{},"value":0},{"type":11,"fromHeroId":{},"toHeroId":{},"value":0},{"type":3,"fromHeroId":52,"toHeroId":{},"value":2},{"type":1000,"fromHeroId":18,"toHeroId":129,"value":50},{"type":1000,"fromHeroId":129,"toHeroId":18,"value":50},{"type":11,"fromHeroId":{},"toHeroId":{},"value":0},{"type":3,"fromHeroId":15,"toHeroId":{},"value":3},{"type":3,"fromHeroId":15,"toHeroId":{},"value":3},{"type":3,"fromHeroId":18,"toHeroId":{},"value":2},{"type":3,"fromHeroId":52,"toHeroId":{},"value":2},{"type":12,"fromHeroId":{},"toHeroId":{},"value":0},{"type":3,"fromHeroId":52,"toHeroId":{},"value":2},{"type":15,"fromHeroId":15,"toHeroId":{},"value":0},{"type":15,"fromHeroId":61,"toHeroId":{},"value":0},{"type":15,"fromHeroId":86,"toHeroId":{},"value":0},{"type":15,"fromHeroId":87,"toHeroId":{},"value":0},{"type":15,"fromHeroId":128,"toHeroId":{},"value":0},{"type":15,"fromHeroId":129,"toHeroId":{},"value":0},{"type":15,"fromHeroId":52,"toHeroId":{},"value":0},{"type":15,"fromHeroId":51,"toHeroId":{},"value":0},{"type":15,"fromHeroId":18,"toHeroId":{},"value":0},{"type":15,"fromHeroId":58,"toHeroId":{},"value":0}],"players":[{"steamAccountId":1171243748,"heroId":18,"dotaPlus":{"level":20}},{"steamAccountId":408729743,"heroId":129,"dotaPlus":{"level":29}},{"steamAccountId":352545711,"heroId":52,"dotaPlus":{"level":24}},{"steamAccountId":119631156,"heroId":58,"dotaPlus":{"level":16}},{"steamAccountId":157989498,"heroId":87,"dotaPlus":{}},{"steamAccountId":86745912,"heroId":15,"dotaPlus":{"level":14}},{"steamAccountId":154715080,"heroId":128,"dotaPlus":{}},{"steamAccountId":126212866,"heroId":61,"dotaPlus":{"level":16}},{"steamAccountId":94155156,"heroId":51,"dotaPlus":{"level":15}},{"steamAccountId":25907144,"heroId":86,"dotaPlus":{"level":24}}]}}
