{"match":{"startDateTime":1689766801,"chatEvents":[{"type":5,"fromHeroId":91,"toHeroId":{},"value":327},{"type":1000,"fromHeroId":86,"toHeroId":41,"value":50},{"type":1000,"fromHeroId":52,"toHeroId":40,"value":50},{"type":10,"fromHeroId":{},"toHeroId":{},"value":0},{"type":11,"fromHeroId":{},"toHeroId":{},"value":0},{"type":114,"fromHeroId":52,"toHeroId":{},"value":7},{"type":11,"fromHeroId":{},"toHeroId":{},"value":0},{"type":12,"fromHeroId":{},"toHeroId":{},"value":0},{"type":12,"fromHeroId":{},"toHeroId":{},"value":0},{"type":3,"fromHeroId":109,"toHeroId":{},"value":2},{"type":114,"fromHeroId":86,"toHeroId":{},"value":1},{"type":1000,"fromHeroId":78,"toHeroId":41,"value":50},{"type":11,"fromHeroId":{},"toHeroId":{},"value":0},{"type":12,"fromHeroId":{},"toHeroId":{},"value":0},{"type":3,"fromHeroId":52,"toHeroId":{},"value":3},{"type":12,"fromHeroId":{},"toHeroId":{},"value":0},{"type":3,"fromHeroId":41,"toHeroId":{},"value":3},{"type":3,"fromHeroId":109,"toHeroId":{},"value":2},{"type":3,"fromHeroId":109,"toHeroId":{},"value":2},{"type":1000,"fromHeroId":78,"toHeroId":107,"value":50},{"type":12,"fromHeroId":{},"toHeroId":{},"value":0},{"type":12,"fromHeroId":{},"toHeroId":{},"value":0},{"type":3,"fromHeroId":109,"toHeroId":{},"value":2},{"type":11,"fromHeroId":{},"toHeroId":{},"value":0},{"type":1000,"fromHeroId":40,"toHeroId":55,"value":50},{"type":3,"fromHeroId":109,"toHeroId":{},"value":2},{"type":12,"fromHeroId":{},"toHeroId":{},"value":0},{"type":3,"fromHeroId":109,"toHeroId":{},"value":2},{"type":12,"fromHeroId":{},"toHeroId":{},"value":0},{"type":3,"fromHeroId":109,"toHeroId":{},"value":2},{"type":3,"fromHeroId":109,"toHeroId":{},"value":2},{"type":91,"fromHeroId":78,"toHeroId":{},"value":0},{"type":10,"fromHeroId":{},"toHeroId":{},"value":0},{"type":15,"fromHeroId":52,"toHeroId":{},"value":0},{"type":15,"fromHeroId":55,"toHeroId":{},"value":0},{"type":15,"fromHeroId":91,"toHeroId":{},"value":0},{"type":15,"fromHeroId":40,"toHeroId":{},"value":0},{"type":15,"fromHeroId":107,"toHeroId":{},"value":0},{"type":15,"fromHeroId":41,"toHeroId":{},"value":0},{"type":15,"fromHeroId":86,"toHeroId":{},"value":0},{"type":15,"fromHeroId":78,"toHeroId":{},"value":0},{"type":15,"fromHeroId":65,"toHeroId":{},"value":0},{"type":15,"fromHeroId":109,"toHeroId":{},"value":0},{"type":11,"fromHeroId":{},"toHeroId":{},"value":0}],"players":[{"steamAccountId":1171243748,"heroId":109,"dotaPlus":{"level":24}},{"steamAccountId":408729743,"heroId":55,"dotaPlus":{"level":30}},{"steamAccountId":352545711,"heroId":65,"dotaPlus":{"level":27}},{"steamAccountId":157989498,"heroId":107,"dotaPlus":{"level":16}},{"steamAccountId":119631156,"heroId":40,"dotaPlus":{}},{"steamAccountId":93618577,"heroId":52,"dotaPlus":{"level":20}},{"steamAccountId":88271237,"heroId":86,"dotaPlus":{"level":12}},{"steamAccountId":167976729,"heroId":41,"dotaPlus":{"level":18}},{"steamAccountId":56351509,"heroId":78,"dotaPlus":{"level":11}},{"steamAccountId":401792574,"heroId":91,"dotaPlus":{"level":27}}]}}
