{"match":{"startDateTime":1690210681,"chatEvents":[{"type":1000,"fromHeroId":8,"toHeroId":17,"value":50},{"type":1000,"fromHeroId":17,"toHeroId":8,"value":50},{"type":11,"fromHeroId":{},"toHeroId":{},"value":0},{"type":5,"fromHeroId":69,"toHeroId":{},"value":374},{"type":12,"fromHeroId":{},"toHeroId":{},"value":0},{"type":12,"fromHeroId":{},"toHeroId":{},"value":0},{"type":12,"fromHeroId":{},"toHeroId":{},"value":0},{"type":12,"fromHeroId":{},"toHeroId":{},"value":0},{"type":3,"fromHeroId":69,"toHeroId":{},"value":3},{"type":114,"fromHeroId":61,"toHeroId":{},"value":0},{"type":3,"fromHeroId":17,"toHeroId":{},"value":2},{"type":12,"fromHeroId":{},"toHeroId":{},"value":0},{"type":1000,"fromHeroId":30,"toHeroId":61,"value":50},{"type":1000,"fromHeroId":8,"toHeroId":61,"value":50},{"type":114,"fromHeroId":58,"toHeroId":{},"value":8},{"type":3,"fromHeroId":61,"toHeroId":{},"value":3},{"type":4,"fromHeroId":17,"toHeroId":{},"value":45},{"type":3,"fromHeroId":58,"toHeroId":{},"value":2},{"type":12,"fromHeroId":{},"toHeroId":{},"value":0},{"type":3,"fromHeroId":4,"toHeroId":{},"value":2},{"type":11,"fromHeroId":{},"toHeroId":{},"value":0},{"type":34,"fromHeroId":65,"toHeroId":{},"value":0},{"type":36,"fromHeroId":71,"toHeroId":{},"value":0},{"type":12,"fromHeroId":{},"toHeroId":{},"value":0},{"type":3,"fromHeroId":61,"toHeroId":{},"value":3},{"type":12,"fromHeroId":{},"toHeroId":{},"value":0},{"type":3,"fromHeroId":30,"toHeroId":{},"value":3},{"type":3,"fromHeroId":61,"toHeroId":{},"value":3},{"type":3,"fromHeroId":8,"toHeroId":{},"value":3},{"type":12,"fromHeroId":{},"toHeroId":{},"value":0},{"type":3,"fromHeroId":8,"toHeroId":{},"value":3},{"type":15,"fromHeroId":4,"toHeroId":{},"value":0},{"type":15,"fromHeroId":98,"toHeroId":{},"value":0},{"type":15,"fromHeroId":8,"toHeroId":{},"value":0},{"type":15,"fromHeroId":17,"toHeroId":{},"value":0},{"type":15,"fromHeroId":58,"toHeroId":{},"value":0},{"type":15,"fromHeroId":69,"toHeroId":{},"value":0},{"type":15,"fromHeroId":71,"toHeroId":{},"value":0},{"type":15,"fromHeroId":65,"toHeroId":{},"value":0},{"type":15,"fromHeroId":61,"toHeroId":{},"value":0},{"type":15,"fromHeroId":30,"toHeroId":{},"value":0}],"players":[{"steamAccountId":292921272,"heroId":98,"dotaPlus":{"level":27}},{"steamAccountId":153836240,"heroId":17,"dotaPlus":{"level":30}},{"steamAccountId":155332459,"heroId":71,"dotaPlus":{}},{"steamAccountId":117089283,"heroId":58,"dotaPlus":{"level":21}},{"steamAccountId":339235645,"heroId":4,"dotaPlus":{"level":11}},{"steamAccountId":134556694,"heroId":30,"dotaPlus":{"level":23}},{"steamAccountId":132851371,"heroId":8,"dotaPlus":{"level":21}},{"steamAccountId":858106446,"heroId":61,"dotaPlus":{"level":26}},{"steamAccountId":161839895,"heroId":65,"dotaPlus":{}},{"steamAccountId":165564598,"heroId":69,"dotaPlus":{"level":24}}]}}
