{"match":{"startDateTime":1692716105,"chatEvents":[{"type":1000,"fromHeroId":106,"toHeroId":101,"value":50},{"type":1000,"fromHeroId":104,"toHeroId":94,"value":50},{"type":5,"fromHeroId":121,"toHeroId":{},"value":332},{"type":12,"fromHeroId":{},"toHeroId":{},"value":0},{"type":12,"fromHeroId":{},"toHeroId":{},"value":0},{"type":3,"fromHeroId":106,"toHeroId":{},"value":3},{"type":3,"fromHeroId":104,"toHeroId":{},"value":2},{"type":12,"fromHeroId":{},"toHeroId":{},"value":0},{"type":3,"fromHeroId":94,"toHeroId":{},"value":3},{"type":12,"fromHeroId":{},"toHeroId":{},"value":0},{"type":3,"fromHeroId":106,"toHeroId":{},"value":3},{"type":3,"fromHeroId":18,"toHeroId":{},"value":2},{"type":11,"fromHeroId":{},"toHeroId":{},"value":0},{"type":3,"fromHeroId":94,"toHeroId":{},"value":3},{"type":3,"fromHeroId":94,"toHeroId":{},"value":3},{"type":12,"fromHeroId":{},"toHeroId":{},"value":0},{"type":3,"fromHeroId":94,"toHeroId":{},"value":3},{"type":12,"fromHeroId":{},"toHeroId":{},"value":0},{"type":11,"fromHeroId":{},"toHeroId":{},"value":0},{"type":3,"fromHeroId":106,"toHeroId":{},"value":3},{"type":3,"fromHeroId":94,"toHeroId":{},"value":3},{"type":15,"fromHeroId":104,"toHeroId":{},"value":0},{"type":15,"fromHeroId":94,"toHeroId":{},"value":0},{"type":15,"fromHeroId":121,"toHeroId":{},"value":0},{"type":15,"fromHeroId":107,"toHeroId":{},"value":0},{"type":15,"fromHeroId":20,"toHeroId":{},"value":0},{"type":15,"fromHeroId":65,"toHeroId":{},"value":0},{"type":15,"fromHeroId":101,"toHeroId":{},"value":0},{"type":15,"fromHeroId":18,"toHeroId":{},"value":0},{"type":15,"fromHeroId":55,"toHeroId":{},"value":0},{"type":11,"fromHeroId":{},"toHeroId":{},"value":0},{"type":15,"fromHeroId":106,"toHeroId":{},"value":0}],"players":[{"steamAccountId":255339080,"heroId":18,"dotaPlus":{}},{"steamAccountId":1131665504,"heroId":65,"dotaPlus":{"level":26}},{"steamAccountId":126174633,"heroId":104,"dotaPlus":{"level":12}},{"steamAccountId":493967542,"heroId":101,"dotaPlus":{"level":15}},{"steamAccountId":99796146,"heroId":20,"dotaPlus":{}},{"steamAccountId":186837494,"heroId":121,"dotaPlus":{}},{"steamAccountId":383867949,"heroId":106,"dotaPlus":{"level":18}},{"steamAccountId":85696663,"heroId":107,"dotaPlus":{"level":22}},{"steamAccountId":155162307,"heroId":94,"dotaPlus":{"level":30}},{"steamAccountId":308163407,"heroId":55,"dotaPlus":{}}]}}
