{"match":{"startDateTime":1693299714,"chatEvents":[{"type":1000,"fromHeroId":20,"toHeroId":94,"value":50},{"type":5,"fromHeroId":83,"toHeroId":{},"value":339},{"type":12,"fromHeroId":{},"toHeroId":{},"value":0},{"type":10,"fromHeroId":{},"toHeroId":{},"value":0},{"type":11,"fromHeroId":{},"toHeroId":{},"value":0},{"type":11,"fromHeroId":{},"toHeroId":{},"value":0},{"type":12,"fromHeroId":{},"toHeroId":{},"value":0},{"type":34,"fromHeroId":86,"toHeroId":{},"value":0},{"type":36,"fromHeroId":93,"toHeroId":{},"value":0},{"type":1000,"fromHeroId":79,"toHeroId":23,"value":50},{"type":1000,"fromHeroId":69,"toHeroId":23,"value":50},{"type":4,"fromHeroId":39,"toHeroId":{},"value":45},{"type":12,"fromHeroId":{},"toHeroId":{},"value":0},{"type":12,"fromHeroId":{},"toHeroId":{},"value":0},{"type":114,"fromHeroId":94,"toHeroId":{},"value":4},{"type":3,"fromHeroId":78,"toHeroId":{},"value":3},{"type":12,"fromHeroId":{},"toHeroId":{},"value":0},{"type":3,"fromHeroId":93,"toHeroId":{},"value":2},{"type":4,"fromHeroId":79,"toHeroId":{},"value":45},{"type":4,"fromHeroId":79,"toHeroId":{},"value":45},{"type":12,"fromHeroId":{},"toHeroId":{},"value":0},{"type":3,"fromHeroId":23,"toHeroId":{},"value":2},{"type":114,"fromHeroId":94,"toHeroId":{},"value":9},{"type":3,"fromHeroId":23,"toHeroId":{},"value":2},{"type":3,"fromHeroId":23,"toHeroId":{},"value":2},{"type":12,"fromHeroId":{},"toHeroId":{},"value":0},{"type":11,"fromHeroId":{},"toHeroId":{},"value":0},{"type":114,"fromHeroId":79,"toHeroId":{},"value":0},{"type":114,"fromHeroId":94,"toHeroId":{},"value":6},{"type":3,"fromHeroId":93,"toHeroId":{},"value":2},{"type":3,"fromHeroId":93,"toHeroId":{},"value":2},{"type":11,"fromHeroId":{},"toHeroId":{},"value":0},{"type":3,"fromHeroId":93,"toHeroId":{},"value":2},{"type":10,"fromHeroId":{},"toHeroId":{},"value":0},{"type":10,"fromHeroId":{},"toHeroId":{},"value":0},{"type":11,"fromHeroId":{},"toHeroId":{},"value":0},{"type":10,"fromHeroId":{},"toHeroId":{},"value":0},{"type":11,"fromHeroId":{},"toHeroId":{},"value":0},{"type":10,"fromHeroId":{},"toHeroId":{},"value":0},{"type":28,"fromHeroId":{},"toHeroId":{},"value":0},{"type":11,"fromHeroId":{},"toHeroId":{},"value":0},{"type":12,"fromHeroId":{},"toHeroId":{},"value":0},{"type":11,"fromHeroId":{},"toHeroId":{},"value":0},{"type":91,"fromHeroId":39,"toHeroId":{},"value":0},{"type":15,"fromHeroId":39,"toHeroId":{},"value":0},{"type":15,"fromHeroId":78,"toHeroId":{},"value":0},{"type":15,"fromHeroId":86,"toHeroId":{},"value":0},{"type":11,"fromHeroId":{},"toHeroId":{},"value":0},{"type":15,"fromHeroId":93,"toHeroId":{},"value":0},{"type":15,"fromHeroId":79,"toHeroId":{},"value":0},{"type":15,"fromHeroId":23,"toHeroId":{},"value":0},{"type":15,"fromHeroId":20,"toHeroId":{},"value":0},{"type":15,"fromHeroId":94,"toHeroId":{},"value":0},{"type":15,"fromHeroId":69,"toHeroId":{},"value":0},{"type":11,"fromHeroId":{},"toHeroId":{},"value":0},{"type":15,"fromHeroId":83,"toHeroId":{},"value":0}],"players":[{"steamAccountId":105045291,"heroId":79,"dotaPlus":{}},{"steamAccountId":208181197,"heroId":23,"dotaPlus":{"level":30}},{"steamAccountId":164962869,"heroId":93,"dotaPlus":{"level":17}},{"steamAccountId":138880576,"heroId":69,"dotaPlus":{"level":14}},{"steamAccountId":73401082,"heroId":20,"dotaPlus":{"level":22}},{"steamAccountId":140297552,"heroId":39,"dotaPlus":{"level":15}},{"steamAccountId":152168157,"heroId":86,"dotaPlus":{"level":20}},{"steamAccountId":320219866,"heroId":83,"dotaPlus":{}},{"steamAccountId":140288368,"heroId":78,"dotaPlus":{"level":15}},{"steamAccountId":96183976,"heroId":94,"dotaPlus":{"level":13}}]}}
