{"match":{"startDateTime":1693411259,"chatEvents":[{"type":1000,"fromHeroId":106,"toHeroId":120,"value":50},{"type":1000,"fromHeroId":120,"toHeroId":106,"value":50},{"type":1000,"fromHeroId":135,"toHeroId":51,"value":50},{"type":5,"fromHeroId":90,"toHeroId":{},"value":330},{"type":1000,"fromHeroId":106,"toHeroId":135,"value":50},{"type":1000,"fromHeroId":51,"toHeroId":135,"value":50},{"type":11,"fromHeroId":{},"toHeroId":{},"value":0},{"type":1000,"fromHeroId":51,"toHeroId":90,"value":50},{"type":11,"fromHeroId":{},"toHeroId":{},"value":0},{"type":1000,"fromHeroId":20,"toHeroId":51,"value":50},{"type":12,"fromHeroId":{},"toHeroId":{},"value":0},{"type":11,"fromHeroId":{},"toHeroId":{},"value":0},{"type":12,"fromHeroId":{},"toHeroId":{},"value":0},{"type":1000,"fromHeroId":120,"toHeroId":106,"value":50},{"type":3,"fromHeroId":135,"toHeroId":{},"value":2},{"type":12,"fromHeroId":{},"toHeroId":{},"value":0},{"type":12,"fromHeroId":{},"toHeroId":{},"value":0},{"type":3,"fromHeroId":106,"toHeroId":{},"value":3},{"type":12,"fromHeroId":{},"toHeroId":{},"value":0},{"type":12,"fromHeroId":{},"toHeroId":{},"value":0},{"type":1000,"fromHeroId":51,"toHeroId":106,"value":50},{"type":3,"fromHeroId":106,"toHeroId":{},"value":3},{"type":1000,"fromHeroId":72,"toHeroId":106,"value":50},{"type":12,"fromHeroId":{},"toHeroId":{},"value":0},{"type":3,"fromHeroId":72,"toHeroId":{},"value":3},{"type":3,"fromHeroId":106,"toHeroId":{},"value":3},{"type":11,"fromHeroId":{},"toHeroId":{},"value":0},{"type":3,"fromHeroId":72,"toHeroId":{},"value":3},{"type":1000,"fromHeroId":104,"toHeroId":72,"value":50},{"type":12,"fromHeroId":{},"toHeroId":{},"value":0},{"type":12,"fromHeroId":{},"toHeroId":{},"value":0},{"type":11,"fromHeroId":{},"toHeroId":{},"value":0},{"type":3,"fromHeroId":72,"toHeroId":{},"value":3},{"type":12,"fromHeroId":{},"toHeroId":{},"value":0},{"type":3,"fromHeroId":72,"toHeroId":{},"value":3},{"type":91,"fromHeroId":94,"toHeroId":{},"value":0},{"type":91,"fromHeroId":72,"toHeroId":{},"value":0},{"type":3,"fromHeroId":72,"toHeroId":{},"value":3},{"type":3,"fromHeroId":72,"toHeroId":{},"value":3},{"type":15,"fromHeroId":72,"toHeroId":{},"value":0},{"type":15,"fromHeroId":20,"toHeroId":{},"value":0},{"type":15,"fromHeroId":120,"toHeroId":{},"value":0},{"type":15,"fromHeroId":106,"toHeroId":{},"value":0},{"type":15,"fromHeroId":79,"toHeroId":{},"value":0},{"type":15,"fromHeroId":94,"toHeroId":{},"value":0},{"type":15,"fromHeroId":104,"toHeroId":{},"value":0},{"type":15,"fromHeroId":51,"toHeroId":{},"value":0},{"type":15,"fromHeroId":90,"toHeroId":{},"value":0},{"type":15,"fromHeroId":135,"toHeroId":{},"value":0}],"players":[{"steamAccountId":105045291,"heroId":90,"dotaPlus":{"level":14}},{"steamAccountId":208181197,"heroId":120,"dotaPlus":{"level":28}},{"steamAccountId":164962869,"heroId":94,"dotaPlus":{"level":18}},{"steamAccountId":138880576,"heroId":135,"dotaPlus":{}},{"steamAccountId":73401082,"heroId":20,"dotaPlus":{"level":22}},{"steamAccountId":171262902,"heroId":72,"dotaPlus":{}},{"steamAccountId":96803083,"heroId":106,"dotaPlus":{"level":24}},{"steamAccountId":127565532,"heroId":51,"dotaPlus":{"level":17}},{"steamAccountId":152545459,"heroId":104,"dotaPlus":{"level":15}},{"steamAccountId":196878136,"heroId":79,"dotaPlus":{"level":12}}]}}
