{"match":{"startDateTime":1693416616,"chatEvents":[{"type":5,"fromHeroId":121,"toHeroId":{},"value":337},{"type":1000,"fromHeroId":23,"toHeroId":38,"value":50},{"type":1000,"fromHeroId":120,"toHeroId":23,"value":50},{"type":12,"fromHeroId":{},"toHeroId":{},"value":0},{"type":1000,"fromHeroId":23,"toHeroId":120,"value":50},{"type":12,"fromHeroId":{},"toHeroId":{},"value":0},{"type":1000,"fromHeroId":15,"toHeroId":38,"value":50},{"type":1000,"fromHeroId":83,"toHeroId":38,"value":50},{"type":12,"fromHeroId":{},"toHeroId":{},"value":0},{"type":1000,"fromHeroId":38,"toHeroId":120,"value":50},{"type":1000,"fromHeroId":83,"toHeroId":38,"value":50},{"type":3,"fromHeroId":23,"toHeroId":{},"value":3},{"type":1000,"fromHeroId":15,"toHeroId":38,"value":50},{"type":3,"fromHeroId":23,"toHeroId":{},"value":3},{"type":1000,"fromHeroId":120,"toHeroId":38,"value":50},{"type":114,"fromHeroId":38,"toHeroId":{},"value":6},{"type":12,"fromHeroId":{},"toHeroId":{},"value":0},{"type":3,"fromHeroId":135,"toHeroId":{},"value":2},{"type":1000,"fromHeroId":120,"toHeroId":135,"value":50},{"type":1000,"fromHeroId":121,"toHeroId":135,"value":50},{"type":114,"fromHeroId":38,"toHeroId":{},"value":1},{"type":3,"fromHeroId":44,"toHeroId":{},"value":2},{"type":12,"fromHeroId":{},"toHeroId":{},"value":0},{"type":12,"fromHeroId":{},"toHeroId":{},"value":0},{"type":3,"fromHeroId":44,"toHeroId":{},"value":2},{"type":3,"fromHeroId":44,"toHeroId":{},"value":2},{"type":10,"fromHeroId":{},"toHeroId":{},"value":0},{"type":12,"fromHeroId":{},"toHeroId":{},"value":0},{"type":3,"fromHeroId":44,"toHeroId":{},"value":2},{"type":3,"fromHeroId":44,"toHeroId":{},"value":2},{"type":12,"fromHeroId":{},"toHeroId":{},"value":0},{"type":11,"fromHeroId":{},"toHeroId":{},"value":0},{"type":3,"fromHeroId":44,"toHeroId":{},"value":2},{"type":12,"fromHeroId":{},"toHeroId":{},"value":0},{"type":34,"fromHeroId":38,"toHeroId":{},"value":0},{"type":36,"fromHeroId":121,"toHeroId":{},"value":0},{"type":3,"fromHeroId":121,"toHeroId":{},"value":2},{"type":15,"fromHeroId":44,"toHeroId":{},"value":0},{"type":15,"fromHeroId":38,"toHeroId":{},"value":0},{"type":15,"fromHeroId":23,"toHeroId":{},"value":0},{"type":15,"fromHeroId":15,"toHeroId":{},"value":0},{"type":15,"fromHeroId":83,"toHeroId":{},"value":0},{"type":15,"fromHeroId":86,"toHeroId":{},"value":0},{"type":15,"fromHeroId":120,"toHeroId":{},"value":0},{"type":15,"fromHeroId":26,"toHeroId":{},"value":0},{"type":15,"fromHeroId":135,"toHeroId":{},"value":0},{"type":15,"fromHeroId":121,"toHeroId":{},"value":0}],"players":[{"steamAccountId":171262902,"heroId":44,"dotaPlus":{"level":17}},{"steamAccountId":96803083,"heroId":120,"dotaPlus":{"level":18}},{"steamAccountId":127565532,"heroId":121,"dotaPlus":{"level":15}},{"steamAccountId":152545459,"heroId":135,"dotaPlus":{"level":11}},{"steamAccountId":196878136,"heroId":86,"dotaPlus":{}},{"steamAccountId":105045291,"heroId":26,"dotaPlus":{"level":13}},{"steamAccountId":208181197,"heroId":23,"dotaPlus":{"level":30}},{"steamAccountId":164962869,"heroId":15,"dotaPlus":{"level":12}},{"steamAccountId":138880576,"heroId":38,"dotaPlus":{"level":22}},{"steamAccountId":73401082,"heroId":83,"dotaPlus":{"level":29}}]}}
