{"match":{"startDateTime":1695130682,"chatEvents":[{"type":1000,"fromHeroId":15,"toHeroId":50,"value":50},{"type":1000,"fromHeroId":19,"toHeroId":90,"value":50},{"type":5,"fromHeroId":53,"toHeroId":{},"value":336},{"type":12,"fromHeroId":{},"toHeroId":{},"value":0},{"type":12,"fromHeroId":{},"toHeroId":{},"value":0},{"type":3,"fromHeroId":17,"toHeroId":{},"value":3},{"type":12,"fromHeroId":{},"toHeroId":{},"value":0},{"type":3,"fromHeroId":50,"toHeroId":{},"value":2},{"type":12,"fromHeroId":{},"toHeroId":{},"value":0},{"type":3,"fromHeroId":17,"toHeroId":{},"value":3},{"type":11,"fromHeroId":{},"toHeroId":{},"value":0},{"type":11,"fromHeroId":{},"toHeroId":{},"value":0},{"type":12,"fromHeroId":{},"toHeroId":{},"value":0},{"type":3,"fromHeroId":109,"toHeroId":{},"value":2},{"type":1000,"fromHeroId":50,"toHeroId":19,"value":50},{"type":1000,"fromHeroId":19,"toHeroId":50,"value":50},{"type":11,"fromHeroId":{},"toHeroId":{},"value":0},{"type":3,"fromHeroId":15,"toHeroId":{},"value":3},{"type":3,"fromHeroId":109,"toHeroId":{},"value":2},{"type":12,"fromHeroId":{},"toHeroId":{},"value":0},{"type":11,"fromHeroId":{},"toHeroId":{},"value":0},{"type":11,"fromHeroId":{},"toHeroId":{},"value":0},{"type":1000,"fromHeroId":19,"toHeroId":109,"value":50},{"type":1000,"fromHeroId":90,"toHeroId":83,"value":50},{"type":11,"fromHeroId":{},"toHeroId":{},"value":0},{"type":1000,"fromHeroId":109,"toHeroId":50,"value":50},{"type":3,"fromHeroId":109,"toHeroId":{},"value":2},{"type":12,"fromHeroId":{},"toHeroId":{},"value":0},{"type":114,"fromHeroId":53,"toHeroId":{},"value":5},{"type":3,"fromHeroId":109,"toHeroId":{},"value":2},{"type":3,"fromHeroId":19,"toHeroId":{},"value":2},{"type":12,"fromHeroId":{},"toHeroId":{},"value":0},{"type":3,"fromHeroId":19,"toHeroId":{},"value":2},{"type":12,"fromHeroId":{},"toHeroId":{},"value":0},{"type":3,"fromHeroId":19,"toHeroId":{},"value":2},{"type":3,"fromHeroId":109,"toHeroId":{},"value":2},{"type":1000,"fromHeroId":109,"toHeroId":90,"value":50},{"type":1000,"fromHeroId":90,"toHeroId":109,"value":50},{"type":1000,"fromHeroId":90,"toHeroId":50,"value":50},{"type":15,"fromHeroId":19,"toHeroId":{},"value":0},{"type":15,"fromHeroId":15,"toHeroId":{},"value":0},{"type":15,"fromHeroId":83,"toHeroId":{},"value":0},{"type":15,"fromHeroId":53,"toHeroId":{},"value":0},{"type":15,"fromHeroId":50,"toHeroId":{},"value":0},{"type":15,"fromHeroId":17,"toHeroId":{},"value":0},{"type":15,"fromHeroId":55,"toHeroId":{},"value":0},{"type":15,"fromHeroId":109,"toHeroId":{},"value":0},{"type":15,"fromHeroId":91,"toHeroId":{},"value":0},{"type":15,"fromHeroId":90,"toHeroId":{},"value":0}],"players":[{"steamAccountId":124801257,"heroId":109,"dotaPlus":{"level":11}},{"steamAccountId":480412663,"heroId":19,"dotaPlus":{"level":17}},{"steamAccountId":331855530,"heroId":50,"dotaPlus":{}},{"steamAccountId":317880638,"heroId":90,"dotaPlus":{"level":23}},{"steamAccountId":431770905,"heroId":83,"dotaPlus":{}},{"steamAccountId":91730177,"heroId":91,"dotaPlus":{}},{"steamAccountId":116934015,"heroId":15,"dotaPlus":{}},{"steamAccountId":97590558,"heroId":55,"dotaPlus":{}},{"steamAccountId":16497807,"heroId":53,"dotaPlus":{"level":13}},{"steamAccountId":221666230,"heroId":17,"dotaPlus":{"level":30}}]}}
