{"match":{"startDateTime":1697239021,"chatEvents":[{"type":34,"fromHeroId":81,"toHeroId":{},"value":0},{"type":1000,"fromHeroId":11,"toHeroId":119,"value":50},{"type":36,"fromHeroId":99,"toHeroId":{},"value":0},{"type":1000,"fromHeroId":36,"toHeroId":99,"value":50},{"type":1000,"fromHeroId":81,"toHeroId":11,"value":50},{"type":1000,"fromHeroId":99,"toHeroId":36,"value":50},{"type":34,"fromHeroId":137,"toHeroId":{},"value":0},{"type":1000,"fromHeroId":7,"toHeroId":99,"value":50},{"type":1000,"fromHeroId":79,"toHeroId":11,"value":50},{"type":36,"fromHeroId":99,"toHeroId":{},"value":0},{"type":34,"fromHeroId":119,"toHeroId":{},"value":0},{"type":15,"fromHeroId":137,"toHeroId":{},"value":0},{"type":1000,"fromHeroId":110,"toHeroId":137,"value":50},{"type":19,"fromHeroId":137,"toHeroId":{},"value":0},{"type":36,"fromHeroId":99,"toHeroId":{},"value":0},{"type":5,"fromHeroId":11,"toHeroId":{},"value":326},{"type":34,"fromHeroId":79,"toHeroId":{},"value":0},{"type":15,"fromHeroId":79,"toHeroId":{},"value":0},{"type":15,"fromHeroId":99,"toHeroId":{},"value":0},{"type":19,"fromHeroId":99,"toHeroId":{},"value":0},{"type":19,"fromHeroId":79,"toHeroId":{},"value":0},{"type":36,"fromHeroId":81,"toHeroId":{},"value":0},{"type":12,"fromHeroId":{},"toHeroId":{},"value":0},{"type":12,"fromHeroId":{},"toHeroId":{},"value":0},{"type":11,"fromHeroId":{},"toHeroId":{},"value":0},{"type":3,"fromHeroId":81,"toHeroId":{},"value":2},{"type":12,"fromHeroId":{},"toHeroId":{},"value":0},{"type":3,"fromHeroId":36,"toHeroId":{},"value":2},{"type":3,"fromHeroId":137,"toHeroId":{},"value":2},{"type":12,"fromHeroId":{},"toHeroId":{},"value":0},{"type":3,"fromHeroId":128,"toHeroId":{},"value":3},{"type":12,"fromHeroId":{},"toHeroId":{},"value":0},{"type":12,"fromHeroId":{},"toHeroId":{},"value":0},{"type":3,"fromHeroId":81,"toHeroId":{},"value":2},{"type":4,"fromHeroId":137,"toHeroId":{},"value":45},{"type":12,"fromHeroId":{},"toHeroId":{},"value":0},{"type":12,"fromHeroId":{},"toHeroId":{},"value":0},{"type":3,"fromHeroId":81,"toHeroId":{},"value":2},{"type":3,"fromHeroId":81,"toHeroId":{},"value":2},{"type":1000,"fromHeroId":81,"toHeroId":79,"value":50},{"type":12,"fromHeroId":{},"toHeroId":{},"value":0},{"type":3,"fromHeroId":119,"toHeroId":{},"value":2},{"type":3,"fromHeroId":81,"toHeroId":{},"value":2},{"type":3,"fromHeroId":81,"toHeroId":{},"value":2},{"type":28,"fromHeroId":{},"toHeroId":{},"value":0},{"type":91,"fromHeroId":79,"toHeroId":{},"value":0},{"type":12,"fromHeroId":{},"toHeroId":{},"value":0},{"type":15,"fromHeroId":11,"toHeroId":{},"value":0},{"type":15,"fromHeroId":99,"toHeroId":{},"value":0},{"type":15,"fromHeroId":137,"toHeroId":{},"value":0},{"type":15,"fromHeroId":119,"toHeroId":{},"value":0},{"type":15,"fromHeroId":79,"toHeroId":{},"value":0},{"type":15,"fromHeroId":36,"toHeroId":{},"value":0},{"type":15,"fromHeroId":7,"toHeroId":{},"value":0},{"type":15,"fromHeroId":110,"toHeroId":{},"value":0},{"type":15,"fromHeroId":81,"toHeroId":{},"value":0},{"type":15,"fromHeroId":128,"toHeroId":{},"value":0}],"players":[{"steamAccountId":91730177,"heroId":110,"dotaPlus":{}},{"steamAccountId":116934015,"heroId":81,"dotaPlus":{"level":18}},{"steamAccountId":97590558,"heroId":137,"dotaPlus":{}},{"steamAccountId":16497807,"heroId":119,"dotaPlus":{"level":20}},{"steamAccountId":221666230,"heroId":36,"dotaPlus":{"level":11}},{"steamAccountId":1171243748,"heroId":11,"dotaPlus":{"level":26}},{"steamAccountId":408729743,"heroId":99,"dotaPlus":{"level":15}},{"steamAccountId":352545711,"heroId":7,"dotaPlus":{"level":12}},{"steamAccountId":157989498,"heroId":128,"dotaPlus":{"level":16}},{"steamAccountId":119631156,"heroId":79,"dotaPlus":{}}]}}
