{"match":{"startDateTime":1697412830,"chatEvents":[{"type":5,"fromHeroId":55,"toHeroId":{},"value":380},{"type":11,"fromHeroId":{},"toHeroId":{},"value":0},{"type":11,"fromHeroId":{},"toHeroId":{},"value":0},{"type":11,"fromHeroId":{},"toHeroId":{},"value":0},{"type":11,"fromHeroId":{},"toHeroId":{},"value":0},{"type":12,"fromHeroId":{},"toHeroId":{},"value":0},{"type":1000,"fromHeroId":119,"toHeroId":81,"value":50},{"type":1000,"fromHeroId":78,"toHeroId":81,"value":50},{"type":3,"fromHeroId":84,"toHeroId":{},"value":2},{"type":11,"fromHeroId":{},"toHeroId":{},"value":0},{"type":12,"fromHeroId":{},"toHeroId":{},"value":0},{"type":4,"fromHeroId":37,"toHeroId":{},"value":45},{"type":3,"fromHeroId":55,"toHeroId":{},"value":3},{"type":3,"fromHeroId":37,"toHeroId":{},"value":3},{"type":12,"fromHeroId":{},"toHeroId":{},"value":0},{"type":12,"fromHeroId":{},"toHeroId":{},"value":0},{"type":3,"fromHeroId":81,"toHeroId":{},"value":2},{"type":10,"fromHeroId":{},"toHeroId":{},"value":0},{"type":3,"fromHeroId":78,"toHeroId":{},"value":2},{"type":11,"fromHeroId":{},"toHeroId":{},"value":0},{"type":3,"fromHeroId":84,"toHeroId":{},"value":2},{"type":12,"fromHeroId":{},"toHeroId":{},"value":0},{"type":3,"fromHeroId":78,"toHeroId":{},"value":2},{"type":12,"fromHeroId":{},"toHeroId":{},"value":0},{"type":3,"fromHeroId":78,"toHeroId":{},"value":2},{"type":3,"fromHeroId":81,"toHeroId":{},"value":2},{"type":28,"fromHeroId":{},"toHeroId":{},"value":0},{"type":3,"fromHeroId":78,"toHeroId":{},"value":2},{"type":12,"fromHeroId":{},"toHeroId":{},"value":0},{"type":15,"fromHeroId":55,"toHeroId":{},"value":0},{"type":15,"fromHeroId":74,"toHeroId":{},"value":0},{"type":15,"fromHeroId":41,"toHeroId":{},"value":0},{"type":15,"fromHeroId":37,"toHeroId":{},"value":0},{"type":15,"fromHeroId":107,"toHeroId":{},"value":0},{"type":15,"fromHeroId":110,"toHeroId":{},"value":0},{"type":15,"fromHeroId":78,"toHeroId":{},"value":0},{"type":15,"fromHeroId":119,"toHeroId":{},"value":0}],"players":[{"steamAccountId":87063175,"heroId":119,"dotaPlus":{}},{"steamAccountId":126238768,"heroId":84,"dotaPlus":{}},{"steamAccountId":81475303,"heroId":110,"dotaPlus":{}},{"steamAccountId":164685175,"heroId":81,"dotaPlus":{"level":11}},{"steamAccountId":84429681,"heroId":78,"dotaPlus":{"level":13}},{"steamAccountId":10366616,"heroId":37,"dotaPlus":{"level":12}},{"steamAccountId":100058342,"heroId":41,"dotaPlus":{"level":29}},{"steamAccountId":94786276,"heroId":107,"dotaPlus":{"level":17}},{"steamAccountId":86698277,"heroId":55,"dotaPlus":{"level":24}},{"steamAccountId":94054712,"heroId":74,"dotaPlus":{"level":30}}]}}
